aws_mp_utils/__init__.py
aws_mp_utils/auth.py
aws_mp_utils/changeset.py
aws_mp_utils/container.py
aws_mp_utils/exceptions.py
aws_mp_utils/image.py
aws_mp_utils/offer.py
aws_mp_utils/scripts/__init__.py
aws_mp_utils/scripts/cli.py
aws_mp_utils/scripts/cli_utils.py
aws_mp_utils/scripts/container.py
aws_mp_utils/scripts/image.py
aws_mp_utils/scripts/offer.py
aws_mp_utils-0.1.0.dist-info/licenses/LICENSE
aws_mp_utils-0.1.0.dist-info/METADATA
aws_mp_utils-0.1.0.dist-info/WHEEL
aws_mp_utils-0.1.0.dist-info/entry_points.txt
aws_mp_utils-0.1.0.dist-info/top_level.txt
aws_mp_utils-0.1.0.dist-info/RECORD
